ipywidgetvar/__init__.py
ipywidgetvar/_version.py
ipywidgetvar/example.py
ipywidgetvar/labextension/package.json
ipywidgetvar/labextension/static/261.0392f0e3c826d0630003.js
ipywidgetvar/labextension/static/261.055b486d4ad27cc85792.js
ipywidgetvar/labextension/static/261.2b07754ed169dbc65202.js
ipywidgetvar/labextension/static/261.322446621ba9fdfda464.js
ipywidgetvar/labextension/static/261.45b50b027bf3d1fb2a85.js
ipywidgetvar/labextension/static/261.497840f89cb7e5409600.js
ipywidgetvar/labextension/static/261.553d95cdb284c537321e.js
ipywidgetvar/labextension/static/261.56037e96c056102a4504.js
ipywidgetvar/labextension/static/261.56c5d40dae0f28856ef4.js
ipywidgetvar/labextension/static/261.73b244d48799ba909c5f.js
ipywidgetvar/labextension/static/261.7672d7dba9aa6e444b77.js
ipywidgetvar/labextension/static/261.7e6ac0b330a1fa35a7e7.js
ipywidgetvar/labextension/static/261.c768ca5757c87a96544e.js
ipywidgetvar/labextension/static/486.32c187ba5ec3f8730a19.js
ipywidgetvar/labextension/static/486.32c187ba5ec3f8730a19.js.LICENSE.txt
ipywidgetvar/labextension/static/568.01bf171bd2ad3ee74179.js
ipywidgetvar/labextension/static/568.13d7a9d0aa1c008de64f.js
ipywidgetvar/labextension/static/568.18ab4e63a22b9098cb9a.js
ipywidgetvar/labextension/static/568.3463c69ec73c4d8df64f.js
ipywidgetvar/labextension/static/568.35ebd78b1955bdc4f64e.js
ipywidgetvar/labextension/static/568.4df9737a45bd075856ae.js
ipywidgetvar/labextension/static/568.67c7d1d462bb7d87280c.js
ipywidgetvar/labextension/static/568.7a194bf51d916d1782bf.js
ipywidgetvar/labextension/static/568.aa3c5c601240c9e3d72e.js
ipywidgetvar/labextension/static/568.d905e1357c964800ac07.js
ipywidgetvar/labextension/static/568.dbde0f855da6a99c87e1.js
ipywidgetvar/labextension/static/568.e63def78dc9cb08100b1.js
ipywidgetvar/labextension/static/568.fc1c725a15d15450d82a.js
ipywidgetvar/labextension/static/remoteEntry.0a60973da4d916772a91.js
ipywidgetvar/labextension/static/remoteEntry.1a895aeef70b136429b2.js
ipywidgetvar-0.1.14a0.dist-info/METADATA
ipywidgetvar-0.1.14a0.dist-info/WHEEL
ipywidgetvar-0.1.14a0.dist-info/top_level.txt
ipywidgetvar-0.1.14a0.dist-info/RECORD
