Metadata-Version: 2.1
Name: ipywidgetvar
Version: 0.1.14a0
Summary: vars between python and js
Home-page: https://github.com/gbrault/ipywidgetvar
Author: Gilbert Brault
Author-email: gbrault@seadev.org
Keywords: ipython,jupyter,widgets
Classifier: Development Status :: 4 - Beta
Classifier: Framework :: IPython
Classifier: Intended Audience :: Developers
Classifier: Intended Audience :: Science/Research
Classifier: Topic :: Multimedia :: Graphics
Classifier: Programming Language :: Python :: 3.6
Classifier: Programming Language :: Python :: 3.7
Classifier: Programming Language :: Python :: 3.8
Classifier: Programming Language :: Python :: 3.9
Requires-Dist: ipywidgets (>=7.6.0)
